README.md
setup.py
vramx/__init__.py
vramx.egg-info/PKG-INFO
vramx.egg-info/SOURCES.txt
vramx.egg-info/dependency_links.txt
vramx.egg-info/top_level.txt