Metadata-Version: 2.1
Name: vramx
Version: 1.6.3
Summary: python vram module
Home-page: https://github.com/zakogarisuki6/vramx
Author: グラファイト
Author-email: gymk@gaypan.jp
Classifier: Programming Language :: Python :: 3
Classifier: Operating System :: OS Independent
Requires-Python: >=3.6
